Workbook

Sheet Mining Websites
A1: Category | B1: Website Name | C1: URL | D1: Focus Area | E1: Geographic Focus | F1: Content Model | G1: Language | H1: Owner / Publisher | I1: Status | J1: Notes
A2: News & Analysis | B2: MINING.COM | C2: https://www.mining.com | D2: General Mining | E2: Global | F2: Freemium | G2: English | H2: Glacier Resource Innovation Group | I2: Active | J2: Self-proclaimed #1 source of global mining news; Mining Power Rankings; owned by Glacier Media
A3: News & Analysis | B3: The Northern Miner | C3: https://www.northernminer.com | D3: General Mining / Precious Metals | E3: Canada / Global | F3: Freemium | G3: English | H3: NMG Media | I3: Active | J3: Founded 1915; Canada's flagship mining publication; print and digital
A4: News & Analysis | B4: Mining Journal | C4: https://www.mining-journal.com | D4: Mining Investment | E4: Global | F4: Subscription | G4: English | H4: Aspermont Ltd | I4: Active | J4: Founded 1835; world's oldest mining publication; data-driven insights, ESG index
A5: News & Analysis | B5: Mining Magazine | C5: https://www.miningmagazine.com | D5: Mining Operations / Technology | E5: Global | F5: Subscription | G5: English | H5: Aspermont Ltd | I5: Active | J5: Operations and technology focused; fleet, automation, digitalisation
A6: News & Analysis | B6: MiningNews.net | C6: https://www.miningnews.net | D6: Mining Investment | E6: Australia | F6: Subscription | G6: English | H6: Aspermont Ltd | I6: Active | J6: Australian mining investment and finance news
A7: News & Analysis | B7: Mining Weekly | C7: https://www.miningweekly.com | D7: General Mining | E7: South Africa / Global | F7: Freemium | G7: English | H7: Creamer Media | I7: Active | J7: South African focus; covers all commodities and African mining
A8: News & Analysis | B8: Canadian Mining Journal | C8: https://www.canadianminingjournal.com | D8: General Mining | E8: Canada | F8: Free | G8: English | H8: Glacier Media | I8: Active | J8: Canada-focused mining industry news since 1882
A9: News & Analysis | B9: Mining Technology | C9: https://www.mining-technology.com | D9: Mining Technology | E9: Global | F9: Free | G9: English | H9: GlobalData | I9: Active | J9: Equipment and technology news; project profiles
A10: News & Analysis | B10: Mining Digital | C10: https://www.miningdigital.com | D10: Mining Technology / Business | E10: Global | F10: Free | G10: English | H10: BizClik Media Group | I10: Active | J10: Digital magazine; top 10 lists; technology and sustainability
A11: News & Analysis | B11: Engineering & Mining Journal (E&MJ) | C11: https://www.e-mj.com | D11: Mining Engineering | E11: Global | F11: Subscription | G11: English | H11: Mining Media International | I11: Active | J11: Founded 1866; engineering and operations focus
A12: News & Analysis | B12: International Mining | C12: https://im-mining.com | D12: Mining Equipment / Operations | E12: Global | F12: Free | G12: English | H12: John Chadwick & Associates | I12: Active | J12: Equipment, operations, and technology coverage
... A135: Bullion & Physical Metals | B135: SD Bullion | C135: https://sdbullion.com | D135: Gold / Silver Bullion | E135: USA | F135: Free | G135: English | H135: SD Bullion Inc. | I135: Active | J135: Low-premium bullion dealer; educational content

Sheet Summary
A1: Category | B1: Total Sites | C1: Free | D1: Freemium | E1: Subscription | F1: Membership / By Invitation
A2: News & Analysis | B2: =COUNTIF('Mining Websites'!A2:A135,A2) -> 15 | C2: =COUNTIFS('Mining Websites'!A2:A135,A2,'Mining Websites'!F2:F135,"Free") -> 7 | D2: =COUNTIFS('Mining Websites'!A2:A135,A2,'Mining Websites'!F2:F135,"Freemium") -> 4 | E2: =COUNTIFS('Mining Websites'!A2:A135,A2,'Mining Websites'!F2:F135,"Subscription") -> 4 | F2: =COUNTIFS('Mining Websites'!A2:A135,A2,'Mining Websites'!F2:F135,"Membership")+COUNTIFS('Mining Websites'!A2:A135,A2,'Mining Websites'!F2:F135,"By Invitation")+COUNTIFS('Mining Websites'!A2:A135,A2,'Mining Websites'!F2:F135,"Paid") -> 0
A3: Precious Metals News | B3: =COUNTIF('Mining Websites'!A2:A135,A3) -> 6 | C3: =COUNTIFS('Mining Websites'!A2:A135,A3,'Mining Websites'!F2:F135,"Free") -> 6 | D3: =COUNTIFS('Mining Websites'!A2:A135,A3,'Mining Websites'!F2:F135,"Freemium") -> 0 | E3: =COUNTIFS('Mining Websites'!A2:A135,A3,'Mining Websites'!F2:F135,"Subscription") -> 0 | F3: =COUNTIFS('Mining Websites'!A2:A135,A3,'Mining Websites'!F2:F135,"Membership")+COUNTIFS('Mining Websites'!A2:A135,A3,'Mining Websites'!F2:F135,"By Invitation")+COUNTIFS('Mining Websites'!A2:A135,A3,'Mining Websites'!F2:F135,"Paid") -> 0
A4: Junior Mining | B4: =COUNTIF('Mining Websites'!A2:A135,A4) -> 6 | C4: =COUNTIFS('Mining Websites'!A2:A135,A4,'Mining Websites'!F2:F135,"Free") -> 3 | D4: =COUNTIFS('Mining Websites'!A2:A135,A4,'Mining Websites'!F2:F135,"Freemium") -> 0 | E4: =COUNTIFS('Mining Websites'!A2:A135,A4,'Mining Websites'!F2:F135,"Subscription") -> 3 | F4: =COUNTIFS('Mining Websites'!A2:A135,A4,'Mining Websites'!F2:F135,"Membership")+COUNTIFS('Mining Websites'!A2:A135,A4,'Mining Websites'!F2:F135,"By Invitation")+COUNTIFS('Mining Websites'!A2:A135,A4,'Mining Websites'!F2:F135,"Paid") -> 0
A5: Commodity Prices & Data | B5: =COUNTIF('Mining Websites'!A2:A135,A5) -> 9 | C5: =COUNTIFS('Mining Websites'!A2:A135,A5,'Mining Websites'!F2:F135,"Free") -> 1 | D5: =COUNTIFS('Mining Websites'!A2:A135,A5,'Mining Websites'!F2:F135,"Freemium") -> 6 | E5: =COUNTIFS('Mining Websites'!A2:A135,A5,'Mining Websites'!F2:F135,"Subscription") -> 2 | F5: =COUNTIFS('Mining Websites'!A2:A135,A5,'Mining Websites'!F2:F135,"Membership")+COUNTIFS('Mining Websites'!A2:A135,A5,'Mining Websites'!F2:F135,"By Invitation")+COUNTIFS('Mining Websites'!A2:A135,A5,'Mining Websites'!F2:F135,"Paid") -> 0
A6: Stock Screeners & Data | B6: =COUNTIF('Mining Websites'!A2:A135,A6) -> 9 | C6: =COUNTIFS('Mining Websites'!A2:A135,A6,'Mining Websites'!F2:F135,"Free") -> 4 | D6: =COUNTIFS('Mining Websites'!A2:A135,A6,'Mining Websites'!F2:F135,"Freemium") -> 4 | E6: =COUNTIFS('Mining Websites'!A2:A135,A6,'Mining Websites'!F2:F135,"Subscription") -> 1 | F6: =COUNTIFS('Mining Websites'!A2:A135,A6,'Mining Websites'!F2:F135,"Membership")+COUNTIFS('Mining Websites'!A2:A135,A6,'Mining Websites'!F2:F135,"By Invitation")+COUNTIFS('Mining Websites'!A2:A135,A6,'Mining Websites'!F2:F135,"Paid") -> 0
A7: Investment Research | B7: =COUNTIF('Mining Websites'!A2:A135,A7) -> 9 | C7: =COUNTIFS('Mining Websites'!A2:A135,A7,'Mining Websites'!F2:F135,"Free") -> 6 | D7: =COUNTIFS('Mining Websites'!A2:A135,A7,'Mining Websites'!F2:F135,"Freemium") -> 1 | E7: =COUNTIFS('Mining Websites'!A2:A135,A7,'Mining Websites'!F2:F135,"Subscription") -> 2 | F7: =COUNTIFS('Mining Websites'!A2:A135,A7,'Mining Websites'!F2:F135,"Membership")+COUNTIFS('Mining Websites'!A2:A135,A7,'Mining Websites'!F2:F135,"By Invitation")+COUNTIFS('Mining Websites'!A2:A135,A7,'Mining Websites'!F2:F135,"Paid") -> 0
A8: Regulatory & Filings | B8: =COUNTIF('Mining Websites'!A2:A135,A8) -> 6 | C8: =COUNTIFS('Mining Websites'!A2:A135,A8,'Mining Websites'!F2:F135,"Free") -> 6 | D8: =COUNTIFS('Mining Websites'!A2:A135,A8,'Mining Websites'!F2:F135,"Freemium") -> 0 | E8: =COUNTIFS('Mining Websites'!A2:A135,A8,'Mining Websites'!F2:F135,"Subscription") -> 0 | F8: =COUNTIFS('Mining Websites'!A2:A135,A8,'Mining Websites'!F2:F135,"Membership")+COUNTIFS('Mining Websites'!A2:A135,A8,'Mining Websites'!F2:F135,"By Invitation")+COUNTIFS('Mining Websites'!A2:A135,A8,'Mining Websites'!F2:F135,"Paid") -> 0
A9: Government & Surveys | B9: =COUNTIF('Mining Websites'!A2:A135,A9) -> 6 | C9: =COUNTIFS('Mining Websites'!A2:A135,A9,'Mining Websites'!F2:F135,"Free") -> 6 | D9: =COUNTIFS('Mining Websites'!A2:A135,A9,'Mining Websites'!F2:F135,"Freemium") -> 0 | E9: =COUNTIFS('Mining Websites'!A2:A135,A9,'Mining Websites'!F2:F135,"Subscription") -> 0 | F9: =COUNTIFS('Mining Websites'!A2:A135,A9,'Mining Websites'!F2:F135,"Membership")+COUNTIFS('Mining Websites'!A2:A135,A9,'Mining Websites'!F2:F135,"By Invitation")+COUNTIFS('Mining Websites'!A2:A135,A9,'Mining Websites'!F2:F135,"Paid") -> 0
A10: Project Databases | B10: =COUNTIF('Mining Websites'!A2:A135,A10) -> 7 | C10: =COUNTIFS('Mining Websites'!A2:A135,A10,'Mining Websites'!F2:F135,"Free") -> 4 | D10: =COUNTIFS('Mining Websites'!A2:A135,A10,'Mining Websites'!F2:F135,"Freemium") -> 1 | E10: =COUNTIFS('Mining Websites'!A2:A135,A10,'Mining Websites'!F2:F135,"Subscription") -> 2 | F10: =COUNTIFS('Mining Websites'!A2:A135,A10,'Mining Websites'!F2:F135,"Membership")+COUNTIFS('Mining Websites'!A2:A135,A10,'Mining Websites'!F2:F135,"By Invitation")+COUNTIFS('Mining Websites'!A2:A135,A10,'Mining Websites'!F2:F135,"Paid") -> 0
A11: Industry Associations | B11: =COUNTIF('Mining Websites'!A2:A135,A11) -> 14 | C11: =COUNTIFS('Mining Websites'!A2:A135,A11,'Mining Websites'!F2:F135,"Free") -> 10 | D11: =COUNTIFS('Mining Websites'!A2:A135,A11,'Mining Websites'!F2:F135,"Freemium") -> 0 | E11: =COUNTIFS('Mining Websites'!A2:A135,A11,'Mining Websites'!F2:F135,"Subscription") -> 0 | F11: =COUNTIFS('Mining Websites'!A2:A135,A11,'Mining Websites'!F2:F135,"Membership")+COUNTIFS('Mining Websites'!A2:A135,A11,'Mining Websites'!F2:F135,"By Invitation")+COUNTIFS('Mining Websites'!A2:A135,A11,'Mining Websites'!F2:F135,"Paid") -> 4
A12: Conferences & Events | B12: =COUNTIF('Mining Websites'!A2:A135,A12) -> 12 | C12: =COUNTIFS('Mining Websites'!A2:A135,A12,'Mining Websites'!F2:F135,"Free") -> 0 | D12: =COUNTIFS('Mining Websites'!A2:A135,A12,'Mining Websites'!F2:F135,"Freemium") -> 0 | E12: =COUNTIFS('Mining Websites'!A2:A135,A12,'Mining Websites'!F2:F135,"Subscription") -> 0 | F12: =COUNTIFS('Mining Websites'!A2:A135,A12,'Mining Websites'!F2:F135,"Membership")+COUNTIFS('Mining Websites'!A2:A135,A12,'Mining Websites'!F2:F135,"By Invitation")+COUNTIFS('Mining Websites'!A2:A135,A12,'Mining Websites'!F2:F135,"Paid") -> 12
A13: Podcasts & Media | B13: =COUNTIF('Mining Websites'!A2:A135,A13) -> 12 | C13: =COUNTIFS('Mining Websites'!A2:A135,A13,'Mining Websites'!F2:F135,"Free") -> 10 | D13: =COUNTIFS('Mining Websites'!A2:A135,A13,'Mining Websites'!F2:F135,"Freemium") -> 2 | E13: =COUNTIFS('Mining Websites'!A2:A135,A13,'Mining Websites'!F2:F135,"Subscription") -> 0 | F13: =COUNTIFS('Mining Websites'!A2:A135,A13,'Mining Websites'!F2:F135,"Membership")+COUNTIFS('Mining Websites'!A2:A135,A13,'Mining Websites'!F2:F135,"By Invitation")+COUNTIFS('Mining Websites'!A2:A135,A13,'Mining Websites'!F2:F135,"Paid") -> 0
A14: Community & Forums | B14: =COUNTIF('Mining Websites'!A2:A135,A14) -> 7 | C14: =COUNTIFS('Mining Websites'!A2:A135,A14,'Mining Websites'!F2:F135,"Free") -> 6 | D14: =COUNTIFS('Mining Websites'!A2:A135,A14,'Mining Websites'!F2:F135,"Freemium") -> 1 | E14: =COUNTIFS('Mining Websites'!A2:A135,A14,'Mining Websites'!F2:F135,"Subscription") -> 0 | F14: =COUNTIFS('Mining Websites'!A2:A135,A14,'Mining Websites'!F2:F135,"Membership")+COUNTIFS('Mining Websites'!A2:A135,A14,'Mining Websites'!F2:F135,"By Invitation")+COUNTIFS('Mining Websites'!A2:A135,A14,'Mining Websites'!F2:F135,"Paid") -> 0
A15: Education & Research | B15: =COUNTIF('Mining Websites'!A2:A135,A15) -> 6 | C15: =COUNTIFS('Mining Websites'!A2:A135,A15,'Mining Websites'!F2:F135,"Free") -> 3 | D15: =COUNTIFS('Mining Websites'!A2:A135,A15,'Mining Websites'!F2:F135,"Freemium") -> 1 | E15: =COUNTIFS('Mining Websites'!A2:A135,A15,'Mining Websites'!F2:F135,"Subscription") -> 0 | F15: =COUNTIFS('Mining Websites'!A2:A135,A15,'Mining Websites'!F2:F135,"Membership")+COUNTIFS('Mining Websites'!A2:A135,A15,'Mining Websites'!F2:F135,"By Invitation")+COUNTIFS('Mining Websites'!A2:A135,A15,'Mining Websites'!F2:F135,"Paid") -> 0
A16: Commodity-Specific | B16: =COUNTIF('Mining Websites'!A2:A135,A16) -> 6 | C16: =COUNTIFS('Mining Websites'!A2:A135,A16,'Mining Websites'!F2:F135,"Free") -> 5 | D16: =COUNTIFS('Mining Websites'!A2:A135,A16,'Mining Websites'!F2:F135,"Freemium") -> 0 | E16: =COUNTIFS('Mining Websites'!A2:A135,A16,'Mining Websites'!F2:F135,"Subscription") -> 1 | F16: =COUNTIFS('Mining Websites'!A2:A135,A16,'Mining Websites'!F2:F135,"Membership")+COUNTIFS('Mining Websites'!A2:A135,A16,'Mining Websites'!F2:F135,"By Invitation")+COUNTIFS('Mining Websites'!A2:A135,A16,'Mining Websites'!F2:F135,"Paid") -> 0
A17: Bullion & Physical Metals | B17: =COUNTIF('Mining Websites'!A2:A135,A17) -> 4 | C17: =COUNTIFS('Mining Websites'!A2:A135,A17,'Mining Websites'!F2:F135,"Free") -> 4 | D17: =COUNTIFS('Mining Websites'!A2:A135,A17,'Mining Websites'!F2:F135,"Freemium") -> 0 | E17: =COUNTIFS('Mining Websites'!A2:A135,A17,'Mining Websites'!F2:F135,"Subscription") -> 0 | F17: =COUNTIFS('Mining Websites'!A2:A135,A17,'Mining Websites'!F2:F135,"Membership")+COUNTIFS('Mining Websites'!A2:A135,A17,'Mining Websites'!F2:F135,"By Invitation")+COUNTIFS('Mining Websites'!A2:A135,A17,'Mining Websites'!F2:F135,"Paid") -> 0
A18: TOTAL | B18: =SUM(B2:B17) -> 134 | C18: =SUM(C2:C17) -> 81 | D18: =SUM(D2:D17) -> 20 | E18: =SUM(E2:E17) -> 15 | F18: =SUM(F2:F17) -> 16
